<?xml version="1.0" encoding="utf-8" ?>
<rsp stat="ok">
<photos page="1" pages="10" perpage="100" total="927">
	<photo id="9412020149" owner="59359109@N07" secret="d7e64aff96" server="3723" farm="4" title="ZZzZzzzZzz... :))" ispublic="1" isfriend="0" isfamily="0" datetaken="2013-07-31 17:07:24" datetakengranularity="0" />
	<photo id="9411407382" owner="59359109@N07" secret="1e8cd8e139" server="7449" farm="8" title="Quissmo... my Prince forever" ispublic="1" isfriend="0" isfamily="0" datetaken="2013-07-31 19:01:14" datetakengranularity="0" />
	<photo id="9351099533" owner="59359109@N07" secret="7996e4ac26" server="5329" farm="6" title="mon Prince ... my Love... Quissmo" ispublic="1" isfriend="0" isfamily="0" datetaken="2013-07-21 12:56:42" datetakengranularity="0" />
	<photo id="9824207655" owner="59359109@N07" secret="57cd5651fd" server="7281" farm="8" title="Quissmo" ispublic="1" isfriend="0" isfamily="0" datetaken="2013-09-19 19:08:10" datetakengranularity="0" />
	<photo id="9788638486" owner="59359109@N07" secret="58a89a8243" server="3707" farm="4" title="Quissmo" ispublic="1" isfriend="0" isfamily="0" datetaken="2013-09-09 19:10:44" datetakengranularity="0" />
	<photo id="8717498591" owner="59359109@N07" secret="0cf1749525" server="7291" farm="8" title="Quissmo" ispublic="1" isfriend="0" isfamily="0" datetaken="2013-05-07 19:17:11" datetakengranularity="0" />
	<photo id="9786561135" owner="59359109@N07" secret="6504e9fedb" server="7411" farm="8" title="Eden" ispublic="1" isfriend="0" isfamily="0" datetaken="2013-07-28 16:31:15" datetakengranularity="0" />
	<photo id="5401432606" owner="38375519@N05" secret="03f51c44ac" server="5259" farm="6" title="Hershey" ispublic="1" isfriend="0" isfamily="0" datetaken="2011-01-29 15:59:04" datetakengranularity="0" />
	<photo id="4708854070" owner="42714591@N03" secret="39a1675cb8" server="4043" farm="5" title="Le doux Elysio" ispublic="1" isfriend="0" isfamily="0" datetaken="2010-06-16 15:13:34" datetakengranularity="0" />
	<photo id="4738089700" owner="42714591@N03" secret="f235fc197d" server="4081" farm="5" title="Tequila" ispublic="1" isfriend="0" isfamily="0" datetaken="2010-06-27 08:55:58" datetakengranularity="0" />
	<photo id="4708212689" owner="42714591@N03" secret="837477ccea" server="4033" farm="5" title="Elysio &amp; Diabolo" ispublic="1" isfriend="0" isfamily="0" datetaken="2010-06-16 15:12:06" datetakengranularity="0" />
	<photo id="4358229240" owner="37424694@N04" secret="5ee3642b2c" server="4064" farm="5" title="Arwen" ispublic="1" isfriend="0" isfamily="0" datetaken="2010-02-14 08:39:16" datetakengranularity="0" />
	<photo id="7330767458" owner="27726982@N04" secret="705a07a909" server="7081" farm="8" title="Connected to that Everything that shapes us. | En comunión con el Todo que nos da forma." ispublic="1" isfriend="0" isfamily="0" datetaken="2012-06-03 17:19:34" datetakengranularity="0" />
	<photo id="6485659195" owner="34613328@N04" secret="090e4fdcb7" server="7162" farm="8" title="Focused" ispublic="1" isfriend="0" isfamily="0" datetaken="2009-02-12 16:59:44" datetakengranularity="0" />
	<photo id="7684136632" owner="37972006@N07" secret="e4622a8b13" server="7108" farm="8" title="CaTaLi's Kazumi" ispublic="1" isfriend="0" isfamily="0" datetaken="2012-07-31 13:17:15" datetakengranularity="0" />
	<photo id="5611324306" owner="8020027@N07" secret="5f241aaf03" server="5101" farm="6" title="Bobbleicious" ispublic="1" isfriend="0" isfamily="0" datetaken="2011-04-08 13:07:42" datetakengranularity="0" />
	<photo id="5451945664" owner="37972006@N07" secret="71a7d8fa7b" server="5298" farm="6" title="Kazumi-chan" ispublic="1" isfriend="0" isfamily="0" datetaken="2011-02-14 12:01:10" datetakengranularity="0" />
	<photo id="5451950454" owner="37972006@N07" secret="b93da88a52" server="4074" farm="5" title="Quentin" ispublic="1" isfriend="0" isfamily="0" datetaken="2011-02-13 11:31:16" datetakengranularity="0" />
	<photo id="4800065084" owner="38608139@N02" secret="65c0df4032" server="4097" farm="5" title="Isaac." ispublic="1" isfriend="0" isfamily="0" datetaken="2010-07-16 11:32:17" datetakengranularity="0" />
	<photo id="8158894749" owner="38608139@N02" secret="7612f26bb3" server="7140" farm="8" title="Zoe Lakota." ispublic="1" isfriend="0" isfamily="0" datetaken="2012-08-30 16:18:08" datetakengranularity="0" />
	<photo id="7331184950" owner="27726982@N04" secret="9204106286" server="7236" farm="8" title="Sacred Birman | Sagrado de Birmania." ispublic="1" isfriend="0" isfamily="0" datetaken="2012-06-03 17:25:21" datetakengranularity="0" />
	<photo id="7684156440" owner="37972006@N07" secret="d0fec55536" server="8423" farm="9" title="CaTaLi's Kazumi" ispublic="1" isfriend="0" isfamily="0" datetaken="2012-07-31 13:15:57" datetakengranularity="0" />
	<photo id="9176041355" owner="38608139@N02" secret="1dbef78140" server="5466" farm="6" title="Zoe sniff... Zoe sniff... Zoe NOM." ispublic="1" isfriend="0" isfamily="0" datetaken="2013-06-02 20:40:21" datetakengranularity="0" />
	<photo id="8270262537" owner="37972006@N07" secret="d789ac1350" server="8488" farm="9" title="CaTaLi's Zoraya, blue tortie tabby point Birman, female, 1 year &amp; 6 months" ispublic="1" isfriend="0" isfamily="0" datetaken="2012-12-13 16:44:41" datetakengranularity="0" />
	<photo id="5429376076" owner="52805340@N02" secret="8e1fa5566c" server="5058" farm="6" title="Our grandpa kitty" ispublic="1" isfriend="0" isfamily="0" datetaken="2011-02-08 10:29:02" datetakengranularity="0" />
	<photo id="6784878502" owner="52805340@N02" secret="26a5a07487" server="7209" farm="8" title="Still a big baby" ispublic="1" isfriend="0" isfamily="0" datetaken="2012-02-09 10:21:14" datetakengranularity="0" />
	<photo id="4846201804" owner="42714591@N03" secret="a495bd62a2" server="4104" farm="5" title="Zoé" ispublic="1" isfriend="0" isfamily="0" datetaken="2010-05-07 12:30:31" datetakengranularity="0" />
	<photo id="9579904378" owner="43199865@N05" secret="746b1d5c38" server="2891" farm="3" title="Birman kitten" ispublic="1" isfriend="0" isfamily="0" datetaken="2013-08-23 22:41:34" datetakengranularity="0" />
	<photo id="8540680452" owner="68329145@N05" secret="8f2fa36a03" server="8391" farm="9" title="La vie d'un chat" ispublic="1" isfriend="0" isfamily="0" datetaken="2013-03-05 14:07:37" datetakengranularity="0" />
	<photo id="4278774413" owner="24283584@N00" secret="7b6247a30d" server="4031" farm="5" title="BURMAN pastel painting" ispublic="1" isfriend="0" isfamily="0" datetaken="2010-01-16 11:58:52" datetakengranularity="0" />
	<photo id="8326230011" owner="38608139@N02" secret="9f37905022" server="8222" farm="9" title="Christmas Ziggy." ispublic="1" isfriend="0" isfamily="0" datetaken="2012-11-22 17:08:25" datetakengranularity="0" />
	<photo id="6869179242" owner="37972006@N07" secret="61fb073901" server="6043" farm="7" title="CaTaLi's Zoraya" ispublic="1" isfriend="0" isfamily="0" datetaken="2012-03-23 12:02:14" datetakengranularity="0" />
	<photo id="7275119284" owner="45957793@N07" secret="5b596c5fb0" server="8020" farm="9" title="Fay" ispublic="1" isfriend="0" isfamily="0" datetaken="2012-05-26 14:50:52" datetakengranularity="0" />
	<photo id="8248479412" owner="38608139@N02" secret="821f9096d9" server="8479" farm="9" title="Zoe Lakota." ispublic="1" isfriend="0" isfamily="0" datetaken="2012-09-26 12:52:05" datetakengranularity="0" />
	<photo id="6783219717" owner="52805340@N02" secret="6cdf5441ff" server="7150" farm="8" title="In the stairs" ispublic="1" isfriend="0" isfamily="0" datetaken="2012-01-29 10:15:09" datetakengranularity="0" />
	<photo id="10819013806" owner="58975350@N06" secret="4121819c15" server="2856" farm="3" title="Photobombing cat" ispublic="1" isfriend="0" isfamily="0" datetaken="2013-11-04 16:14:55" datetakengranularity="0" />
	<photo id="7684143494" owner="37972006@N07" secret="e7d4eb3fd4" server="7249" farm="8" title="CaTaLi's Kazumi" ispublic="1" isfriend="0" isfamily="0" datetaken="2012-07-31 13:16:32" datetakengranularity="0" />
	<photo id="4516583870" owner="93314694@N00" secret="f3b3322f74" server="2238" farm="3" title="Birman Cat" ispublic="1" isfriend="0" isfamily="0" datetaken="2010-04-12 21:55:51" datetakengranularity="0" />
	<photo id="7990975479" owner="42714591@N03" secret="69482d425c" server="8454" farm="9" title="Wallace" ispublic="1" isfriend="0" isfamily="0" datetaken="2012-09-16 08:29:55" datetakengranularity="0" />
	<photo id="7684161078" owner="37972006@N07" secret="e03e39586d" server="7278" farm="8" title="CaTaLi's Kazumi" ispublic="1" isfriend="0" isfamily="0" datetaken="2012-07-31 13:13:29" datetakengranularity="0" />
	<photo id="7015205651" owner="37972006@N07" secret="cd6e864c4d" server="6057" farm="7" title="CaTaLi's Zoraya" ispublic="1" isfriend="0" isfamily="0" datetaken="2012-03-23 11:57:51" datetakengranularity="0" />
	<photo id="5274186576" owner="42714591@N03" secret="cac133e481" server="5208" farm="6" title="4 you my friends" ispublic="1" isfriend="0" isfamily="0" datetaken="2010-12-19 14:39:25" datetakengranularity="0" />
	<photo id="4708212411" owner="42714591@N03" secret="06bc5ffd0d" server="1303" farm="2" title="Elysio, Dino &amp; Diabolo" ispublic="1" isfriend="0" isfamily="0" datetaken="2010-06-16 15:07:53" datetakengranularity="0" />
	<photo id="10444114104" owner="83830592@N02" secret="7dcd45546f" server="2870" farm="3" title="Zazu" ispublic="1" isfriend="0" isfamily="0" datetaken="2013-09-22 12:22:00" datetakengranularity="0" />
	<photo id="7684149498" owner="37972006@N07" secret="0d52662333" server="8027" farm="9" title="CaTaLi's Kazumi" ispublic="1" isfriend="0" isfamily="0" datetaken="2012-07-31 13:16:01" datetakengranularity="0" />
	<photo id="5761131216" owner="42714591@N03" secret="d3f308bf15" server="3572" farm="4" title="." ispublic="1" isfriend="0" isfamily="0" datetaken="2011-05-22 09:35:27" datetakengranularity="0" />
	<photo id="4872814708" owner="42714591@N03" secret="9ebe4a8dd2" server="4078" farm="5" title="Zoé" ispublic="1" isfriend="0" isfamily="0" datetaken="2010-08-08 20:37:35" datetakengranularity="0" />
	<photo id="8158895947" owner="38608139@N02" secret="ddbf61bebc" server="8207" farm="9" title="Zoe &amp; Ziggy." ispublic="1" isfriend="0" isfamily="0" datetaken="2012-08-30 16:16:42" datetakengranularity="0" />
	<photo id="7684172030" owner="37972006@N07" secret="bb0464efc6" server="8020" farm="9" title="I'm a a little bit of heaven with a wild side" ispublic="1" isfriend="0" isfamily="0" datetaken="2012-07-31 13:10:04" datetakengranularity="0" />
	<photo id="5943887866" owner="37972006@N07" secret="3a7e4c349d" server="6014" farm="7" title="Kazumi" ispublic="1" isfriend="0" isfamily="0" datetaken="2011-07-16 18:01:58" datetakengranularity="0" />
	<photo id="9186364556" owner="38608139@N02" secret="a3196e387b" server="7448" farm="8" title="Zoe Lakota." ispublic="1" isfriend="0" isfamily="0" datetaken="2013-04-09 17:37:54" datetakengranularity="0" />
	<photo id="9186214498" owner="38608139@N02" secret="5f70b5e90e" server="3676" farm="4" title="Ziggy." ispublic="1" isfriend="0" isfamily="0" datetaken="2013-04-09 17:36:33" datetakengranularity="0" />
	<photo id="4274467960" owner="46559203@N02" secret="54ef7b8ace" server="4006" farm="5" title="Willow in Wicker" ispublic="1" isfriend="0" isfamily="0" datetaken="2013-07-27 19:17:10" datetakengranularity="0" />
	<photo id="8271324202" owner="37972006@N07" secret="41a01b05f9" server="8221" farm="9" title="CaTaLi's Kazumi, chocolate tabby point Birman, female, 3 years &amp; 1 month" ispublic="1" isfriend="0" isfamily="0" datetaken="2012-12-07 12:26:33" datetakengranularity="0" />
	<photo id="5001452096" owner="42714591@N03" secret="5ccb1b5eee" server="4104" farm="5" title="" ispublic="1" isfriend="0" isfamily="0" datetaken="2010-09-18 15:49:31" datetakengranularity="0" />
	<photo id="4872815284" owner="42714591@N03" secret="6192decae7" server="4118" farm="5" title="Zoé" ispublic="1" isfriend="0" isfamily="0" datetaken="2010-08-08 20:38:26" datetakengranularity="0" />
	<photo id="3722863539" owner="28730502@N07" secret="99ac26a2ec" server="2446" farm="3" title="Birman Cat Licking Nose" ispublic="1" isfriend="0" isfamily="0" datetaken="2009-04-23 15:43:10" datetakengranularity="0" />
	<photo id="9184163117" owner="38608139@N02" secret="9b299f1468" server="5324" farm="6" title="Zoe Lakota." ispublic="1" isfriend="0" isfamily="0" datetaken="2013-04-09 17:37:57" datetakengranularity="0" />
	<photo id="5129153715" owner="50404124@N05" secret="086fc60f3b" server="4003" farm="5" title="DSC_3560" ispublic="1" isfriend="0" isfamily="0" datetaken="2010-10-30 11:10:18" datetakengranularity="0" />
	<photo id="8649766420" owner="51167579@N06" secret="deb4292166" server="8524" farm="9" title="Mia-Kat Sketching Kit" ispublic="1" isfriend="0" isfamily="0" datetaken="2013-04-07 12:35:47" datetakengranularity="0" />
	<photo id="2318950523" owner="23540353@N04" secret="0f9a2ec2ee" server="2237" farm="3" title="FEED ME!" ispublic="1" isfriend="0" isfamily="0" datetaken="2008-03-08 09:41:27" datetakengranularity="0" />
	<photo id="6869145796" owner="37972006@N07" secret="2fd9b40a97" server="7079" farm="8" title="CaTaLi's Kazumi" ispublic="1" isfriend="0" isfamily="0" datetaken="2012-03-23 11:59:10" datetakengranularity="0" />
	<photo id="6135665445" owner="52805340@N02" secret="bc98938b70" server="6061" farm="7" title="7 lives" ispublic="1" isfriend="0" isfamily="0" datetaken="2011-09-11 13:18:35" datetakengranularity="0" />
	<photo id="6371282411" owner="29261858@N04" secret="5a852e29ca" server="6219" farm="7" title="Birman" ispublic="1" isfriend="0" isfamily="0" datetaken="2011-11-12 14:05:04" datetakengranularity="0" />
	<photo id="4800063550" owner="38608139@N02" secret="9018ae20fd" server="4082" farm="5" title="Isaac." ispublic="1" isfriend="0" isfamily="0" datetaken="2010-07-16 11:31:39" datetakengranularity="0" />
	<photo id="8248481848" owner="38608139@N02" secret="8baa36bdfc" server="8205" farm="9" title="Ziggy." ispublic="1" isfriend="0" isfamily="0" datetaken="2012-09-26 12:47:53" datetakengranularity="0" />
	<photo id="4399936144" owner="48012500@N04" secret="a8ef283bc6" server="4022" farm="5" title="Birman" ispublic="1" isfriend="0" isfamily="0" datetaken="2010-03-01 15:50:04" datetakengranularity="0" />
	<photo id="3722861783" owner="28730502@N07" secret="47c624ef39" server="2613" farm="3" title="Birman Cat Crying" ispublic="1" isfriend="0" isfamily="0" datetaken="2009-04-23 15:43:04" datetakengranularity="0" />
	<photo id="4708212217" owner="42714591@N03" secret="d8c8e79129" server="4010" farm="5" title="Dino" ispublic="1" isfriend="0" isfamily="0" datetaken="2010-06-16 15:04:40" datetakengranularity="0" />
	<photo id="4518786685" owner="93314694@N00" secret="f97ea22b2d" server="2697" farm="3" title="Birman Cat 2" ispublic="1" isfriend="0" isfamily="0" datetaken="2010-04-12 23:03:52" datetakengranularity="0" />
	<photo id="7668904306" owner="37972006@N07" secret="4d39677425" server="8013" farm="9" title="CaTaLi&amp;#39;s Kazumi" ispublic="1" isfriend="0" isfamily="0" datetaken="2012-07-29 16:18:55" datetakengranularity="0" />
	<photo id="4300777898" owner="45957793@N07" secret="256f31c08d" server="4048" farm="5" title="Simba" ispublic="1" isfriend="0" isfamily="0" datetaken="2010-01-24 11:50:06" datetakengranularity="0" />
	<photo id="4238067404" owner="34960319@N04" secret="2b73c54565" server="2543" farm="3" title="Cat Plane Body" ispublic="1" isfriend="0" isfamily="0" datetaken="2010-01-02 13:45:35" datetakengranularity="0" />
	<photo id="6267746130" owner="29261858@N04" secret="9e10051a3c" server="6052" farm="7" title="Birman" ispublic="1" isfriend="0" isfamily="0" datetaken="2011-09-24 10:41:31" datetakengranularity="0" />
	<photo id="250933093" owner="51807909@N00" secret="8296a79bd7" server="99" farm="1" title="misha" ispublic="1" isfriend="0" isfamily="0" datetaken="2006-09-23 19:14:53" datetakengranularity="0" />
	<photo id="8290311005" owner="83978951@N08" secret="512e66f7fd" server="8072" farm="9" title="Angel eyes, for now." ispublic="1" isfriend="0" isfamily="0" datetaken="2012-12-20 12:49:41" datetakengranularity="0" />
	<photo id="5997640316" owner="52805340@N02" secret="ae6ba4402d" server="6133" farm="7" title="Can I have some peace &amp; quiet please?!" ispublic="1" isfriend="0" isfamily="0" datetaken="2011-07-29 17:43:31" datetakengranularity="0" />
	<photo id="4089294249" owner="21031300@N02" secret="a8b057ef02" server="2686" farm="3" title="Tumble dryers" ispublic="1" isfriend="0" isfamily="0" datetaken="2007-01-01 20:01:39" datetakengranularity="0" />
	<photo id="5001451976" owner="42714591@N03" secret="8461dfce62" server="4104" farm="5" title="" ispublic="1" isfriend="0" isfamily="0" datetaken="2010-09-18 15:49:28" datetakengranularity="0" />
	<photo id="5451947476" owner="37972006@N07" secret="18e67e4028" server="5054" farm="6" title="Quentin" ispublic="1" isfriend="0" isfamily="0" datetaken="2011-02-11 14:57:38" datetakengranularity="0" />
	<photo id="4852844684" owner="42714591@N03" secret="8734d6b0d6" server="4094" farm="5" title="Elysio" ispublic="1" isfriend="0" isfamily="0" datetaken="2010-06-16 15:09:26" datetakengranularity="0" />
	<photo id="8158897361" owner="38608139@N02" secret="f7b1bbd0e9" server="7280" farm="8" title="Zoe Lakota." ispublic="1" isfriend="0" isfamily="0" datetaken="2012-08-30 16:06:36" datetakengranularity="0" />
	<photo id="6277213125" owner="37972006@N07" secret="42e88ddf21" server="6059" farm="7" title="CaTaLi's Zoraya 4 months old" ispublic="1" isfriend="0" isfamily="0" datetaken="2011-10-11 16:48:10" datetakengranularity="0" />
	<photo id="4708854772" owner="42714591@N03" secret="a22871f4aa" server="4049" farm="5" title="Elysio" ispublic="1" isfriend="0" isfamily="0" datetaken="2010-06-16 15:31:49" datetakengranularity="0" />
	<photo id="4956799514" owner="42714591@N03" secret="e4d69e54c3" server="4105" farm="5" title="" ispublic="1" isfriend="0" isfamily="0" datetaken="2010-09-04 12:05:06" datetakengranularity="0" />
	<photo id="2416698610" owner="21708988@N02" secret="273a40c506" server="2085" farm="3" title="Thinking cat" ispublic="1" isfriend="0" isfamily="0" datetaken="2004-01-01 00:00:00" datetakengranularity="0" />
	<photo id="8248484070" owner="38608139@N02" secret="997d606542" server="8069" farm="9" title="Ziggy." ispublic="1" isfriend="0" isfamily="0" datetaken="2012-09-26 12:45:04" datetakengranularity="0" />
	<photo id="7355628896" owner="37972006@N07" secret="d456113277" server="8021" farm="9" title="CaTaLi's Zoraya" ispublic="1" isfriend="0" isfamily="0" datetaken="2012-06-08 14:32:39" datetakengranularity="0" />
	<photo id="5240284275" owner="34518483@N06" secret="0f7531f898" server="5088" farm="6" title="Susi (Bum hat cat)" ispublic="1" isfriend="0" isfamily="0" datetaken="2009-04-11 10:28:00" datetakengranularity="0" />
	<photo id="4916093122" owner="42714591@N03" secret="3f20bd7a37" server="4118" farm="5" title="" ispublic="1" isfriend="0" isfamily="0" datetaken="2010-06-16 15:31:21" datetakengranularity="0" />
	<photo id="4915490151" owner="42714591@N03" secret="28d2cafdf5" server="4136" farm="5" title="" ispublic="1" isfriend="0" isfamily="0" datetaken="2010-06-16 15:31:38" datetakengranularity="0" />
	<photo id="4708854484" owner="42714591@N03" secret="556b0cca72" server="4043" farm="5" title="Dino" ispublic="1" isfriend="0" isfamily="0" datetaken="2010-06-16 15:31:38" datetakengranularity="0" />
	<photo id="7510570868" owner="37972006@N07" secret="20202c4eed" server="7247" farm="8" title="CaTaLi's Kazumi" ispublic="1" isfriend="0" isfamily="0" datetaken="2012-07-05 13:53:23" datetakengranularity="0" />
	<photo id="5044372630" owner="42714591@N03" secret="616a9438c2" server="4106" farm="5" title="Princesse Zoé" ispublic="1" isfriend="0" isfamily="0" datetaken="2010-10-02 15:53:27" datetakengranularity="0" />
	<photo id="3674718753" owner="23474360@N06" secret="ef871758d3" server="2578" farm="3" title="Private Moments (Toffee)" ispublic="1" isfriend="0" isfamily="0" datetaken="2009-06-30 07:36:23" datetakengranularity="0" />
	<photo id="1975834326" owner="44901254@N00" secret="c5f11695af" server="2101" farm="3" title="Chucky I~~My Favorite, taken by my niece, Lisa+++" ispublic="1" isfriend="0" isfamily="0" datetaken="2007-11-11 21:09:50" datetakengranularity="0" />
	<photo id="5663773509" owner="7363619@N02" secret="7b2825dc10" server="5190" farm="6" title="B/W ~ Melody" ispublic="1" isfriend="0" isfamily="0" datetaken="2011-04-28 11:59:54" datetakengranularity="0" />
	<photo id="2415877515" owner="21708988@N02" secret="05ef5c09fd" server="3095" farm="4" title="The Bat Cat" ispublic="1" isfriend="0" isfamily="0" datetaken="2004-01-01 00:00:00" datetakengranularity="0" />
</photos>
</rsp>
